pfolio/__init__.py
pfolio/analyses/__init__.py
pfolio/analyses/attribution_analysis/__init__.py
pfolio/analyses/comparative_analysis/__init__.py
pfolio/analyses/drawdown_analysis/__init__.py
pfolio/analyses/factor_analysis/__init__.py
pfolio/analyses/performance_analysis/__init__.py
pfolio/analyses/risk_analysis/__init__.py
pfolio/analyses/scenario_analysis/__init__.py
pfolio/analytics/__init__.py
pfolio/analytics/ratios.py
pfolio/analytics/returns.py
pfolio/analytics/risks.py
pfolio/config.py
pfolio/main.py
pfolio/optimizers/__init__.py
pfolio/statistics/__init__.py
pfolio/utils/utils.py
pfolio-0.0.2.dist-info/LICENSE
pfolio-0.0.2.dist-info/METADATA
pfolio-0.0.2.dist-info/WHEEL
pfolio-0.0.2.dist-info/entry_points.txt
pfolio-0.0.2.dist-info/RECORD
